matplotlips/__init__.py
matplotlips/arrays.py
matplotlips/charts.py
matplotlips-8.8.8.dist-info/METADATA
matplotlips-8.8.8.dist-info/WHEEL
matplotlips-8.8.8.dist-info/top_level.txt
matplotlips-8.8.8.dist-info/RECORD
